hyperion/__init__.py
hyperion/hyp_defs.py
hyperion/hyp_model.py
hyperion/model_loader.py
hyperion/augment/__init__.py
hyperion/augment/noise_augment.py
hyperion/augment/reverb_augment.py
hyperion/augment/speech_augment.py
hyperion/augment/speed_augment.py
hyperion/calibration/__init__.py
hyperion/calibration/gauss_calibration.py
hyperion/calibration/unsup_gauss_calibration.py
hyperion/classifiers/__init__.py
hyperion/classifiers/binary_logistic_regression.py
hyperion/classifiers/greedy_fusion.py
hyperion/classifiers/linear_gbe.py
hyperion/classifiers/linear_gbe1.py
hyperion/classifiers/linear_gbe_up.py
hyperion/classifiers/linear_svmc.py
hyperion/classifiers/logistic_regression.py
hyperion/classifiers/q_scoring_homo_gbe.py
hyperion/clustering/__init__.py
hyperion/clustering/ahc.py
hyperion/clustering/kmeans.py
hyperion/diarization/__init__.py
hyperion/diarization/diar_ahc_plda.py
hyperion/feats/__init__.py
hyperion/feats/energy_vad.py
hyperion/feats/feature_normalization.py
hyperion/feats/feature_windows.py
hyperion/feats/filter_banks.py
hyperion/feats/frame_selector.py
hyperion/feats/mfcc.py
hyperion/feats/stft.py
hyperion/helpers/__init__.py
hyperion/helpers/classif_trial_data_reader.py
hyperion/helpers/multi_test_trial_data_reader.py
hyperion/helpers/multi_test_trial_data_reader_v2.py
hyperion/helpers/plda_factory.py
hyperion/helpers/tracking_data_reader.py
hyperion/helpers/trial_data_reader.py
hyperion/helpers/vector_class_reader.py
hyperion/helpers/vector_reader.py
hyperion/io/__init__.py
hyperion/io/ark_data_reader.py
hyperion/io/ark_data_writer.py
hyperion/io/audio_reader.py
hyperion/io/audio_writer.py
hyperion/io/bin_vad_reader.py
hyperion/io/copy_feats.py
hyperion/io/data_reader.py
hyperion/io/data_rw_factory.py
hyperion/io/data_writer.py
hyperion/io/h5_data_reader.py
hyperion/io/h5_data_writer.py
hyperion/io/h5_merger.py
hyperion/io/hyp_data_reader.py
hyperion/io/hyp_data_writer.py
hyperion/io/int32_writer.py
hyperion/io/kaldi_data_reader.py
hyperion_ml-0.3.2.dist-info/LICENSE
hyperion_ml-0.3.2.dist-info/METADATA
hyperion_ml-0.3.2.dist-info/WHEEL
hyperion_ml-0.3.2.dist-info/top_level.txt
hyperion_ml-0.3.2.dist-info/RECORD
