Metadata-Version: 2.1
Name: hyperion-ml
Version: 0.3.2
Summary: Toolkit for speaker recognition
Home-page: https://github.com/hyperion-ml/hyperion
Author: Jesus Villalba
Author-email: jesus.antonio.villalba@gmail.com
License: UNKNOWN
Keywords: speaker recognition,adversarial attacks,NIST SRE,x-vectors
Platform: UNKNOWN
Classifier: Programming Language :: Python :: 3
Classifier: Programming Language :: Python :: 3.7
Classifier: Programming Language :: Python :: 3.8
Classifier: License :: OSI Approved :: Apache Software License
Classifier: Operating System :: OS Independent
Requires-Python: >=3.7
Requires-Dist: torch (>=1.9.0)
Requires-Dist: numpy (>=1.18.1)
Requires-Dist: h5py (>=2.10.0)
Requires-Dist: pysoundfile (>=0.9.0)
Requires-Dist: matplotlib (>=3.1.3)
Requires-Dist: pandas (>=1.0.1)
Requires-Dist: scikit-learn (>=0.22.1)
Requires-Dist: scipy (>=1.4.1)
Requires-Dist: sphinx-rtd-theme (>=0.4.3)
Requires-Dist: pympler
Requires-Dist: memory-profiler
Requires-Dist: gdown
Requires-Dist: fairscale (==0.4.4)
Requires-Dist: tensorboard (>=2.5.0)
Requires-Dist: yapf
Requires-Dist: jsonargparse (>=3.5.0)
Requires-Dist: wandb (>=0.10.30)
Requires-Dist: librosa (>=0.8.1)
Requires-Dist: black
Requires-Dist: twine
Requires-Dist: wheel
